Metadata-Version: 1.0
Name: adxl345
Version: 1.0.3
Summary: Python module to use ADXL345.
Home-page: https://github.com/alcalyn/adxl345
Author: Alcalyn
Author-email: doubjulien@hotmail.fr
License: MIT
Platform: UNKNOWN
